pydefender/__init__.py
pydefender/abc.py
pydefender/constants.py
pydefender/pydefender.py
pydefender/types.py
pydefender/modules/AntiAnalysis.py
pydefender/modules/AntiDll.py
pydefender/modules/AntiDump.py
pydefender/modules/AntiProcess.py
pydefender/modules/AntiVM.py
pydefender/modules/Miscellaneous.py
pydefender/modules/__init__.py
pydefender/utils/__init__.py
pydefender/utils/events.py
pydefender/utils/exceptions.py
pydefender/utils/http.py
pydefender/utils/webhook.py
pydefender/utils/windows.py
pythondefender-1.0.4.dist-info/LICENSE
pythondefender-1.0.4.dist-info/METADATA
pythondefender-1.0.4.dist-info/WHEEL
pythondefender-1.0.4.dist-info/top_level.txt
pythondefender-1.0.4.dist-info/RECORD
