Metadata-Version: 2.1
Name: pythondefender
Version: 1.0.4
Summary: A simple, easy-to-use Python file protector.
Home-page: https://github.com/faintastic/PyDefender
Author: Faint / Kova
Author-email: faintastic@pm.me
License: MIT
Keywords: protect,protection,defend,defender,obfuscate,obfuscation,pydefend,pydefender
Classifier: Development Status :: 4 - Beta
Classifier: Intended Audience :: Developers
Classifier: Operating System :: Microsoft :: Windows :: Windows 10
Classifier: Operating System :: Microsoft :: Windows :: Windows 11
Classifier: Natural Language :: English
Classifier: Topic :: Education
Classifier: Topic :: Internet
License-File: LICENSE
Requires-Dist: humanize
Requires-Dist: loguru
Requires-Dist: discord-webhook
Requires-Dist: py-cpuinfo
Requires-Dist: command-runner
Requires-Dist: psutil
Requires-Dist: httpx
Requires-Dist: WMI
Requires-Dist: pywin32
Requires-Dist: Pillow
Requires-Dist: observable
Requires-Dist: cryptography
Requires-Dist: pythondefender
